processional/__init__.py
processional/__main__.py
processional/connection.py
processional/host.py
processional/processing.py
processional/shared.py
processional/threading.py
processional-0.1.4.dist-info/LICENSE
processional-0.1.4.dist-info/METADATA
processional-0.1.4.dist-info/WHEEL
processional-0.1.4.dist-info/RECORD
