Metadata-Version: 2.3
Name: processional
Version: 0.1.4
Summary: multiprocess and multithread functional programming library
License: LGPL-3.0
Author: jimy-byerley
Author-email: jimy.byerley@gmail.com
Requires-Python: >=3.9
Classifier: License :: OSI Approved :: GNU Lesser General Public License v3 (LGPLv3)
Classifier: Programming Language :: Python :: 3
Classifier: Programming Language :: Python :: 3.9
Classifier: Programming Language :: Python :: 3.10
Classifier: Programming Language :: Python :: 3.11
Classifier: Programming Language :: Python :: 3.12
Classifier: Programming Language :: Python :: 3.13
Requires-Dist: dill (>=0.3.9,<0.4.0)
